embcli_voyage/__init__.py
embcli_voyage/py.typed
embcli_voyage/voyage.py
embcli_voyage/voyage_multimodal.py
embcli_voyage-0.1.2.dist-info/METADATA
embcli_voyage-0.1.2.dist-info/WHEEL
embcli_voyage-0.1.2.dist-info/entry_points.txt
embcli_voyage-0.1.2.dist-info/RECORD
